msise00/CMakeLists.txt
msise00/__init__.py
msise00/__main__.py
msise00/base.py
msise00/plots.py
msise00/timeutils.py
msise00/worldgrid.py
msise00/fortran/msise00_data.f
msise00/fortran/msise00_driver.f90
msise00/fortran/msise00_sub.f
msise00/tests/__init__.py
msise00/tests/test_ccmc.py
msise00/tests/test_grid.py
msise00/tests/test_module.py
msise00/tests/test_point.py
msise00/tests/test_time_grid.py
msise00-1.11.1.dist-info/LICENSE.txt
msise00-1.11.1.dist-info/METADATA
msise00-1.11.1.dist-info/WHEEL
msise00-1.11.1.dist-info/top_level.txt
msise00-1.11.1.dist-info/RECORD
