Metadata-Version: 2.1
Name: msise00
Version: 1.11.1
Summary: Python API for Fortran MSISE-00 neutral atmosphere model.
Keywords: atmosphere,geospace
Classifier: Development Status :: 5 - Production/Stable
Classifier: Environment :: Console
Classifier: Intended Audience :: Science/Research
Classifier: Operating System :: OS Independent
Classifier: Programming Language :: Fortran
Classifier: Programming Language :: Python :: 3
Classifier: Topic :: Scientific/Engineering :: Atmospheric Science
Requires-Python: >=3.9
License-File: LICENSE.txt
Requires-Dist: python-dateutil
Requires-Dist: numpy
Requires-Dist: xarray
Requires-Dist: geomagindices>=1.4.0
Provides-Extra: tests
Requires-Dist: pytest; extra == "tests"
Requires-Dist: netCDF4; extra == "tests"
Provides-Extra: lint
Requires-Dist: flake8; extra == "lint"
Requires-Dist: flake8-bugbear; extra == "lint"
Requires-Dist: flake8-builtins; extra == "lint"
Requires-Dist: flake8-blind-except; extra == "lint"
Requires-Dist: mypy; extra == "lint"
Requires-Dist: types-python-dateutil; extra == "lint"
Provides-Extra: plot
Requires-Dist: matplotlib; extra == "plot"
Requires-Dist: astropy; extra == "plot"
Requires-Dist: seaborn; extra == "plot"
Requires-Dist: pymap3d; extra == "plot"
